common_crud/__init__.py
common_crud/base_crud.py
common_crud/exceptions.py
common_crud/py.typed
common_crud-0.1.4.dist-info/METADATA
common_crud-0.1.4.dist-info/WHEEL
common_crud-0.1.4.dist-info/RECORD
