Metadata-Version: 2.3
Name: common-crud
Version: 0.1.4
Summary: Common CRUD operations for SQLAlchemy and FastAPI
License: MIT
Author: smdsu
Author-email: 109036946+smdsu@users.noreply.github.com
Requires-Python: >=3.10
Classifier: License :: OSI Approved :: MIT License
Classifier: Programming Language :: Python :: 3
Classifier: Programming Language :: Python :: 3.10
Classifier: Programming Language :: Python :: 3.11
Classifier: Programming Language :: Python :: 3.12
Classifier: Programming Language :: Python :: 3.13
Requires-Dist: sqlalchemy (>=2.0.40,<3.0.0)
